ash/__init__.py
ash/apps.py
ash/filters.py
ash/settings.py
ash/migrations/__init__.py
ash/static/admin/css/autocomplete.css
ash/static/admin/css/forms.css
ash/static/admin/css/widgets.css
ash/static/admin/datta-able/css/style.css
ash/static/admin/datta-able/css/vazir-fonts.css
ash/static/admin/datta-able/css/layout/rtl.css
ash/static/admin/datta-able/fonts/datta/datta-icon.css
ash/static/admin/datta-able/fonts/datta/fonts/pct.eot
ash/static/admin/datta-able/fonts/datta/fonts/pct.svg
ash/static/admin/datta-able/fonts/datta/fonts/pct.ttf
ash/static/admin/datta-able/fonts/datta/fonts/pct.woff
ash/static/admin/datta-able/fonts/feather/css/feather.css
ash/static/admin/datta-able/fonts/feather/fonts/feather.eot
ash/static/admin/datta-able/fonts/feather/fonts/feather.svg
ash/static/admin/datta-able/fonts/feather/fonts/feather.ttf
ash/static/admin/datta-able/fonts/feather/fonts/feather.woff
ash/static/admin/datta-able/fonts/fontawesome/css/fontawesome-all.min.css
ash/static/admin/datta-able/fonts/fontawesome/webfonts/fa-brands-400.eot
ash/static/admin/datta-able/fonts/fontawesome/webfonts/fa-brands-400.svg
ash/static/admin/datta-able/fonts/fontawesome/webfonts/fa-brands-400.ttf
ash/static/admin/datta-able/fonts/fontawesome/webfonts/fa-brands-400.woff
ash/static/admin/datta-able/fonts/fontawesome/webfonts/fa-brands-400.woff2
ash/static/admin/datta-able/fonts/fontawesome/webfonts/fa-regular-400.eot
ash/static/admin/datta-able/fonts/fontawesome/webfonts/fa-regular-400.svg
ash/static/admin/datta-able/fonts/fontawesome/webfonts/fa-regular-400.ttf
ash/static/admin/datta-able/fonts/fontawesome/webfonts/fa-regular-400.woff
ash/static/admin/datta-able/fonts/fontawesome/webfonts/fa-regular-400.woff2
ash/static/admin/datta-able/fonts/fontawesome/webfonts/fa-solid-900.eot
ash/static/admin/datta-able/fonts/fontawesome/webfonts/fa-solid-900.svg
ash/static/admin/datta-able/fonts/fontawesome/webfonts/fa-solid-900.ttf
ash/static/admin/datta-able/fonts/fontawesome/webfonts/fa-solid-900.woff
django_ash-0.0.8.dist-info/licenses/LICENSE
django_ash-0.0.8.dist-info/METADATA
django_ash-0.0.8.dist-info/WHEEL
django_ash-0.0.8.dist-info/top_level.txt
django_ash-0.0.8.dist-info/RECORD
